tracelog/__init__.py
tracelog/function.py
tracelog/main.py
tracelog-0.0.5.dist-info/METADATA
tracelog-0.0.5.dist-info/WHEEL
tracelog-0.0.5.dist-info/top_level.txt
tracelog-0.0.5.dist-info/RECORD
