Metadata-Version: 2.1
Name: tracelog
Version: 0.0.5
Requires-Dist: requests
Requires-Dist: importlib ; python_version == "3.8"
